cst_ui/__init__.py
cst_ui/basic/app/__init__.py
cst_ui/basic/app/data_admin.py
cst_ui/basic/app/flet_app.py
cst_ui/basic/app/inheritance.py
cst_ui/basic/app/jwt.py
cst_ui/basic/app/my_types.py
cst_ui/basic/app/page_admin.py
cst_ui/basic/app/route.py
cst_ui/basic/app/view_404.py
cst_ui-0.0.2.dist-info/METADATA
cst_ui-0.0.2.dist-info/WHEEL
cst_ui-0.0.2.dist-info/RECORD
